client/__init__.py
client/client_database.py
client/main_window.py
client/main_window_conv.py
client/transport.py
client/welcome_window.py
common/__init__.py
common/decos.py
common/errors.py
common/metaclasses.py
common/utils.py
common/variables.py
logs/__init__.py
logs/client_log_config.py
Byunichenko_DB_and_PyQt_client_module-0.0.1.dist-info/METADATA
Byunichenko_DB_and_PyQt_client_module-0.0.1.dist-info/WHEEL
Byunichenko_DB_and_PyQt_client_module-0.0.1.dist-info/top_level.txt
Byunichenko_DB_and_PyQt_client_module-0.0.1.dist-info/RECORD
